{
	"id": "nXWCcxaWfyt4H8y",
	"json": "{\"id\":\"nXWCcxaWfyt4H8y\",\"url\":\"https://www.starbucks.com.tr/menu/icecekler/turk-kahvesi\",\"loadedUrl\":\"https://www.starbucks.com.tr/en/menu\",\"uniqueKey\":\"https://www.starbucks.com.tr/menu/icecekler/turk-kahvesi\",\"method\":\"GET\",\"noRetry\":false,\"retryCount\":0,\"errorMessages\":[],\"headers\":{},\"userData\":{\"__crawlee\":{\"state\":4}},\"handledAt\":\"2026-03-16T08:19:13.268Z\"}",
	"method": "GET",
	"orderNo": null,
	"retryCount": 0,
	"uniqueKey": "https://www.starbucks.com.tr/menu/icecekler/turk-kahvesi",
	"url": "https://www.starbucks.com.tr/menu/icecekler/turk-kahvesi"
}